timc_vector_toolkit/__init__.py
timc_vector_toolkit/__main__.py
timc_vector_toolkit/_readme.md
timc_vector_toolkit-20250919.dist-info/WHEEL
timc_vector_toolkit-20250919.dist-info/METADATA
timc_vector_toolkit-20250919.dist-info/RECORD
