Metadata-Version: 2.3
Name: timc-vector-toolkit
Version: 20250919
Summary: Ensemble package for all Tutte Institute librairies involved in data vectorization, dimension reduction, clustering and exploratory visualization
Author: Benoit Hamelin
Author-email: Benoit Hamelin <benoit.hamelin@cyber.gc.ca>
Requires-Dist: datamapplot>=0.6.4
Requires-Dist: einops>=0.8.1
Requires-Dist: evoc>=0.1.3
Requires-Dist: fast-hdbscan>=0.2.2
Requires-Dist: glasbey>=0.3.0
Requires-Dist: hdbscan>=0.8.40
Requires-Dist: ipykernel>=6.30.1
Requires-Dist: toponymy>=0.3.0
Requires-Dist: tqdm>=4.67.1
Requires-Dist: umap-learn[plot]>=0.5.8
Requires-Dist: vectorizers>=0.2.2
Requires-Python: >=3.10
